odoo/addons/survey_next_survey_update_partner/README.rst
odoo/addons/survey_next_survey_update_partner/__init__.py
odoo/addons/survey_next_survey_update_partner/__manifest__.py
odoo/addons/survey_next_survey_update_partner/demo/survey_update_generated_partner_demo.xml
odoo/addons/survey_next_survey_update_partner/i18n/it.po
odoo/addons/survey_next_survey_update_partner/i18n/survey_next_survey_update_partner.pot
odoo/addons/survey_next_survey_update_partner/models/__init__.py
odoo/addons/survey_next_survey_update_partner/models/survey_user_input.py
odoo/addons/survey_next_survey_update_partner/readme/CONTEXT.md
odoo/addons/survey_next_survey_update_partner/readme/CONTRIBUTORS.md
odoo/addons/survey_next_survey_update_partner/readme/DESCRIPTION.md
odoo/addons/survey_next_survey_update_partner/readme/USAGE.md
odoo/addons/survey_next_survey_update_partner/static/description/icon.png
odoo/addons/survey_next_survey_update_partner/static/description/index.html
odoo/addons/survey_next_survey_update_partner/static/tests/survey_contact_update_tour.esm.js
odoo/addons/survey_next_survey_update_partner/tests/__init__.py
odoo/addons/survey_next_survey_update_partner/tests/test_next_survey_update_partner.py
odoo_addon_survey_next_survey_update_partner-17.0.1.0.0.4.dist-info/METADATA
odoo_addon_survey_next_survey_update_partner-17.0.1.0.0.4.dist-info/WHEEL
odoo_addon_survey_next_survey_update_partner-17.0.1.0.0.4.dist-info/top_level.txt
odoo_addon_survey_next_survey_update_partner-17.0.1.0.0.4.dist-info/RECORD
