Metadata-Version: 2.1
Name: odoo-addon-survey_next_survey_update_partner
Version: 17.0.1.0.0.4
Requires-Python: >=3.10
Requires-Dist: odoo-addon-survey_answer_generation>=17.0dev,<17.1dev
Requires-Dist: odoo-addon-survey_contact_generation>=17.0dev,<17.1dev
Requires-Dist: odoo>=17.0a,<17.1dev
Summary: Update the partner values when it's generated from the previous survey
Home-page: https://github.com/OCA/survey
License: AGPL-3
Author: Tecnativa, Odoo Community Association (OCA)
Author-email: support@odoo-community.org
Classifier: Programming Language :: Python
Classifier: Framework :: Odoo
Classifier: Framework :: Odoo :: 17.0
Classifier: License :: OSI Approved :: GNU Affero General Public License v3
Classifier: Development Status :: 4 - Beta
